{"namedChunkGroups":{"polyfill":{"name":"polyfill","assets":[{"name":"webpack-runtime-fc24e9dc83e30f5f4af5.js","size":7895},{"name":"polyfill-ff4e3d2c3de56734b40c.js","size":82649}],"filteredAssets":0,"assetsSize":90544,"filteredAuxiliaryAssets":2,"auxiliaryAssetsSize":224453},"app":{"name":"app","assets":[{"name":"webpack-runtime-fc24e9dc83e30f5f4af5.js","size":7895},{"name":"framework-cdc12ae707ed0f1084a8.js","size":130668},{"name":"app-5c34450b26552dd01bca.js","size":84800}],"filteredAssets":0,"assetsSize":223363,"filteredAuxiliaryAssets":3,"auxiliaryAssetsSize":697949},"component---src-pages-404-tsx":{"name":"component---src-pages-404-tsx","assets":[{"name":"framework-cdc12ae707ed0f1084a8.js","size":130668},{"name":"styles.191266c70ed3461c11b7.css","size":168809},{"name":"a9a7754c-e01654b7e0389317be23.js","size":4849},{"name":"cb1608f2-e6adf9bb6fd20bfed239.js","size":7589},{"name":"commons-8817f1dc13b8b3f15631.js","size":95151},{"name":"d9d9aac2f06cd78624aede3022e388915c13e40b-ec74eb48eac289eceb98.js","size":51358},{"name":"component---src-pages-404-tsx-1c40a00572d6d52a2abf.js","size":2696}],"filteredAssets":0,"assetsSize":461120,"filteredAuxiliaryAssets":6,"auxiliaryAssetsSize":2169507},"component---src-pages-about-dataprot-tsx":{"name":"component---src-pages-about-dataprot-tsx","assets":[{"name":"framework-cdc12ae707ed0f1084a8.js","size":130668},{"name":"styles.191266c70ed3461c11b7.css","size":168809},{"name":"a9a7754c-e01654b7e0389317be23.js","size":4849},{"name":"commons-8817f1dc13b8b3f15631.js","size":95151},{"name":"d9d9aac2f06cd78624aede3022e388915c13e40b-ec74eb48eac289eceb98.js","size":51358},{"name":"component---src-pages-about-dataprot-tsx-972697101debce014674.js","size":12197}],"filteredAssets":0,"assetsSize":463032,"filteredAuxiliaryAssets":5,"auxiliaryAssetsSize":1455626},"component---src-pages-about-imprint-tsx":{"name":"component---src-pages-about-imprint-tsx","assets":[{"name":"framework-cdc12ae707ed0f1084a8.js","size":130668},{"name":"styles.191266c70ed3461c11b7.css","size":168809},{"name":"a9a7754c-e01654b7e0389317be23.js","size":4849},{"name":"commons-8817f1dc13b8b3f15631.js","size":95151},{"name":"d9d9aac2f06cd78624aede3022e388915c13e40b-ec74eb48eac289eceb98.js","size":51358},{"name":"component---src-pages-about-imprint-tsx-7e69737dab1ce7a1123e.js","size":3974}],"filteredAssets":0,"assetsSize":454809,"filteredAuxiliaryAssets":5,"auxiliaryAssetsSize":1446512},"component---src-pages-about-index-tsx":{"name":"component---src-pages-about-index-tsx","assets":[{"name":"framework-cdc12ae707ed0f1084a8.js","size":130668},{"name":"styles.191266c70ed3461c11b7.css","size":168809},{"name":"a9a7754c-e01654b7e0389317be23.js","size":4849},{"name":"commons-8817f1dc13b8b3f15631.js","size":95151},{"name":"d9d9aac2f06cd78624aede3022e388915c13e40b-ec74eb48eac289eceb98.js","size":51358},{"name":"component---src-pages-about-index-tsx-df2bae44c065a443a78e.js","size":3946}],"filteredAssets":0,"assetsSize":454781,"filteredAuxiliaryAssets":5,"auxiliaryAssetsSize":1446656},"component---src-pages-about-team-tsx":{"name":"component---src-pages-about-team-tsx","assets":[{"name":"framework-cdc12ae707ed0f1084a8.js","size":130668},{"name":"styles.191266c70ed3461c11b7.css","size":168809},{"name":"a9a7754c-e01654b7e0389317be23.js","size":4849},{"name":"commons-8817f1dc13b8b3f15631.js","size":95151},{"name":"d9d9aac2f06cd78624aede3022e388915c13e40b-ec74eb48eac289eceb98.js","size":51358},{"name":"component---src-pages-about-team-tsx-d283fe40da3f04233a3c.js","size":11453}],"filteredAssets":0,"assetsSize":462288,"filteredAuxiliaryAssets":5,"auxiliaryAssetsSize":1468617},"component---src-pages-cms-index-tsx":{"name":"component---src-pages-cms-index-tsx","assets":[{"name":"framework-cdc12ae707ed0f1084a8.js","size":130668},{"name":"styles.191266c70ed3461c11b7.css","size":168809},{"name":"a9a7754c-e01654b7e0389317be23.js","size":4849},{"name":"commons-8817f1dc13b8b3f15631.js","size":95151},{"name":"d9d9aac2f06cd78624aede3022e388915c13e40b-ec74eb48eac289eceb98.js","size":51358},{"name":"component---src-pages-cms-index-tsx-eed145157b0403b82486.js","size":3993}],"filteredAssets":0,"assetsSize":454828,"filteredAuxiliaryAssets":5,"auxiliaryAssetsSize":1447471},"component---src-pages-collection-tsx":{"name":"component---src-pages-collection-tsx","assets":[{"name":"framework-cdc12ae707ed0f1084a8.js","size":130668},{"name":"styles.191266c70ed3461c11b7.css","size":168809},{"name":"a9a7754c-e01654b7e0389317be23.js","size":4849},{"name":"cb1608f2-e6adf9bb6fd20bfed239.js","size":7589},{"name":"commons-8817f1dc13b8b3f15631.js","size":95151},{"name":"d9d9aac2f06cd78624aede3022e388915c13e40b-ec74eb48eac289eceb98.js","size":51358},{"name":"component---src-pages-collection-tsx-129f2bb0cf3de2bcf453.js","size":10202}],"filteredAssets":0,"assetsSize":468626,"filteredAuxiliaryAssets":6,"auxiliaryAssetsSize":2200180},"component---src-pages-demo-tsx":{"name":"component---src-pages-demo-tsx","assets":[{"name":"framework-cdc12ae707ed0f1084a8.js","size":130668},{"name":"styles.191266c70ed3461c11b7.css","size":168809},{"name":"a9a7754c-e01654b7e0389317be23.js","size":4849},{"name":"commons-8817f1dc13b8b3f15631.js","size":95151},{"name":"d9d9aac2f06cd78624aede3022e388915c13e40b-ec74eb48eac289eceb98.js","size":51358},{"name":"component---src-pages-demo-tsx-e16ebc523747eeca418d.js","size":2086}],"filteredAssets":0,"assetsSize":452921,"filteredAuxiliaryAssets":5,"auxiliaryAssetsSize":1444353},"component---src-pages-doc-authorization-tsx":{"name":"component---src-pages-doc-authorization-tsx","assets":[{"name":"framework-cdc12ae707ed0f1084a8.js","size":130668},{"name":"styles.191266c70ed3461c11b7.css","size":168809},{"name":"a9a7754c-e01654b7e0389317be23.js","size":4849},{"name":"commons-8817f1dc13b8b3f15631.js","size":95151},{"name":"d9d9aac2f06cd78624aede3022e388915c13e40b-ec74eb48eac289eceb98.js","size":51358},{"name":"701dc261555fcc3a9aac6dcd63ecb7e55ca62dbb-c11d7d1f21ef991cac01.js","size":11833},{"name":"component---src-pages-doc-authorization-tsx-f27885b1532db5bbc9f9.js","size":3295}],"filteredAssets":0,"assetsSize":465963,"filteredAuxiliaryAssets":6,"auxiliaryAssetsSize":1484276},"component---src-pages-doc-datamodel-tsx":{"name":"component---src-pages-doc-datamodel-tsx","assets":[{"name":"framework-cdc12ae707ed0f1084a8.js","size":130668},{"name":"styles.191266c70ed3461c11b7.css","size":168809},{"name":"a9a7754c-e01654b7e0389317be23.js","size":4849},{"name":"commons-8817f1dc13b8b3f15631.js","size":95151},{"name":"d9d9aac2f06cd78624aede3022e388915c13e40b-ec74eb48eac289eceb98.js","size":51358},{"name":"component---src-pages-doc-datamodel-tsx-50ed787cd8bb51c2f033.js","size":5966}],"filteredAssets":0,"assetsSize":456801,"filteredAuxiliaryAssets":5,"auxiliaryAssetsSize":1457054},"component---src-pages-doc-faq-tsx":{"name":"component---src-pages-doc-faq-tsx","assets":[{"name":"framework-cdc12ae707ed0f1084a8.js","size":130668},{"name":"styles.191266c70ed3461c11b7.css","size":168809},{"name":"a9a7754c-e01654b7e0389317be23.js","size":4849},{"name":"commons-8817f1dc13b8b3f15631.js","size":95151},{"name":"d9d9aac2f06cd78624aede3022e388915c13e40b-ec74eb48eac289eceb98.js","size":51358},{"name":"701dc261555fcc3a9aac6dcd63ecb7e55ca62dbb-c11d7d1f21ef991cac01.js","size":11833},{"name":"component---src-pages-doc-faq-tsx-a5257416cb25f374a339.js","size":1162}],"filteredAssets":0,"assetsSize":463830,"filteredAuxiliaryAssets":6,"auxiliaryAssetsSize":1483444},"component---src-pages-doc-howto-tsx":{"name":"component---src-pages-doc-howto-tsx","assets":[{"name":"framework-cdc12ae707ed0f1084a8.js","size":130668},{"name":"styles.191266c70ed3461c11b7.css","size":168809},{"name":"a9a7754c-e01654b7e0389317be23.js","size":4849},{"name":"commons-8817f1dc13b8b3f15631.js","size":95151},{"name":"d9d9aac2f06cd78624aede3022e388915c13e40b-ec74eb48eac289eceb98.js","size":51358},{"name":"701dc261555fcc3a9aac6dcd63ecb7e55ca62dbb-c11d7d1f21ef991cac01.js","size":11833},{"name":"component---src-pages-doc-howto-tsx-d7743cea65f64cc16e5b.js","size":1351}],"filteredAssets":0,"assetsSize":464019,"filteredAuxiliaryAssets":6,"auxiliaryAssetsSize":1483886},"component---src-pages-doc-index-tsx":{"name":"component---src-pages-doc-index-tsx","assets":[{"name":"framework-cdc12ae707ed0f1084a8.js","size":130668},{"name":"styles.191266c70ed3461c11b7.css","size":168809},{"name":"a9a7754c-e01654b7e0389317be23.js","size":4849},{"name":"commons-8817f1dc13b8b3f15631.js","size":95151},{"name":"d9d9aac2f06cd78624aede3022e388915c13e40b-ec74eb48eac289eceb98.js","size":51358},{"name":"component---src-pages-doc-index-tsx-0fdaa484a15b2e77ab52.js","size":9389}],"filteredAssets":0,"assetsSize":460224,"filteredAuxiliaryAssets":5,"auxiliaryAssetsSize":1461115},"component---src-pages-eshop-index-tsx":{"name":"component---src-pages-eshop-index-tsx","assets":[{"name":"framework-cdc12ae707ed0f1084a8.js","size":130668},{"name":"styles.191266c70ed3461c11b7.css","size":168809},{"name":"a9a7754c-e01654b7e0389317be23.js","size":4849},{"name":"commons-8817f1dc13b8b3f15631.js","size":95151},{"name":"d9d9aac2f06cd78624aede3022e388915c13e40b-ec74eb48eac289eceb98.js","size":51358},{"name":"19cf059346695348b71b701879ad247a7424ad83-9101f486d176e4f17994.js","size":14559},{"name":"component---src-pages-eshop-index-tsx-086e9ecaffc69f738a69.js","size":9745}],"filteredAssets":0,"assetsSize":475139,"filteredAuxiliaryAssets":6,"auxiliaryAssetsSize":1522381},"component---src-pages-events-index-tsx":{"name":"component---src-pages-events-index-tsx","assets":[{"name":"framework-cdc12ae707ed0f1084a8.js","size":130668},{"name":"styles.191266c70ed3461c11b7.css","size":168809},{"name":"a9a7754c-e01654b7e0389317be23.js","size":4849},{"name":"commons-8817f1dc13b8b3f15631.js","size":95151},{"name":"d9d9aac2f06cd78624aede3022e388915c13e40b-ec74eb48eac289eceb98.js","size":51358},{"name":"component---src-pages-events-index-tsx-9d236a385a63020aa71e.js","size":7955}],"filteredAssets":0,"assetsSize":458790,"filteredAuxiliaryAssets":5,"auxiliaryAssetsSize":1463188},"component---src-pages-exhibitions-identities-final-page-index-tsx":{"name":"component---src-pages-exhibitions-identities-final-page-index-tsx","assets":[{"name":"framework-cdc12ae707ed0f1084a8.js","size":130668},{"name":"styles.191266c70ed3461c11b7.css","size":168809},{"name":"commons-8817f1dc13b8b3f15631.js","size":95151},{"name":"fa7506b98c3597319d30ed7c7d3a27e4fe8c02d7-572af4f1cd9f19672a94.js","size":19434},{"name":"19cf059346695348b71b701879ad247a7424ad83-9101f486d176e4f17994.js","size":14559},{"name":"component---src-pages-exhibitions-identities-final-page-index-tsx-cf180af46ae31d4a218b.js","size":7393}],"filteredAssets":0,"assetsSize":436014,"filteredAuxiliaryAssets":5,"auxiliaryAssetsSize":838962},"component---src-pages-exhibitions-identities-intro-index-tsx":{"name":"component---src-pages-exhibitions-identities-intro-index-tsx","assets":[{"name":"framework-cdc12ae707ed0f1084a8.js","size":130668},{"name":"styles.191266c70ed3461c11b7.css","size":168809},{"name":"commons-8817f1dc13b8b3f15631.js","size":95151},{"name":"fa7506b98c3597319d30ed7c7d3a27e4fe8c02d7-572af4f1cd9f19672a94.js","size":19434},{"name":"component---src-pages-exhibitions-identities-intro-index-tsx-a7c9a494c5e360bc2168.js","size":9756}],"filteredAssets":0,"assetsSize":423818,"filteredAuxiliaryAssets":4,"auxiliaryAssetsSize":789754},"component---src-pages-exhibitions-identities-obj-one-index-tsx":{"name":"component---src-pages-exhibitions-identities-obj-one-index-tsx","assets":[{"name":"framework-cdc12ae707ed0f1084a8.js","size":130668},{"name":"styles.191266c70ed3461c11b7.css","size":168809},{"name":"commons-8817f1dc13b8b3f15631.js","size":95151},{"name":"fa7506b98c3597319d30ed7c7d3a27e4fe8c02d7-572af4f1cd9f19672a94.js","size":19434},{"name":"component---src-pages-exhibitions-identities-obj-one-index-tsx-173c04837a6c78c71803.js","size":8686}],"filteredAssets":0,"assetsSize":422748,"filteredAuxiliaryAssets":4,"auxiliaryAssetsSize":787932},"component---src-pages-exhibitions-identities-question-four-index-tsx":{"name":"component---src-pages-exhibitions-identities-question-four-index-tsx","assets":[{"name":"framework-cdc12ae707ed0f1084a8.js","size":130668},{"name":"styles.191266c70ed3461c11b7.css","size":168809},{"name":"commons-8817f1dc13b8b3f15631.js","size":95151},{"name":"fa7506b98c3597319d30ed7c7d3a27e4fe8c02d7-572af4f1cd9f19672a94.js","size":19434},{"name":"19cf059346695348b71b701879ad247a7424ad83-9101f486d176e4f17994.js","size":14559},{"name":"component---src-pages-exhibitions-identities-question-four-index-tsx-a9a8176fbf0fde3e2bf3.js","size":6769}],"filteredAssets":0,"assetsSize":435390,"filteredAuxiliaryAssets":5,"auxiliaryAssetsSize":837784},"component---src-pages-exhibitions-identities-question-one-index-tsx":{"name":"component---src-pages-exhibitions-identities-question-one-index-tsx","assets":[{"name":"framework-cdc12ae707ed0f1084a8.js","size":130668},{"name":"styles.191266c70ed3461c11b7.css","size":168809},{"name":"commons-8817f1dc13b8b3f15631.js","size":95151},{"name":"fa7506b98c3597319d30ed7c7d3a27e4fe8c02d7-572af4f1cd9f19672a94.js","size":19434},{"name":"component---src-pages-exhibitions-identities-question-one-index-tsx-134cc1b84c1cf222c533.js","size":3864}],"filteredAssets":0,"assetsSize":417926,"filteredAuxiliaryAssets":4,"auxiliaryAssetsSize":775420},"component---src-pages-exhibitions-index-tsx":{"name":"component---src-pages-exhibitions-index-tsx","assets":[{"name":"framework-cdc12ae707ed0f1084a8.js","size":130668},{"name":"styles.191266c70ed3461c11b7.css","size":168809},{"name":"commons-8817f1dc13b8b3f15631.js","size":95151},{"name":"fa7506b98c3597319d30ed7c7d3a27e4fe8c02d7-572af4f1cd9f19672a94.js","size":19434},{"name":"component---src-pages-exhibitions-index-tsx-9f41d7998cd3de55d0d1.js","size":2143}],"filteredAssets":0,"assetsSize":416205,"filteredAuxiliaryAssets":4,"auxiliaryAssetsSize":770811},"component---src-pages-factsheets-index-tsx":{"name":"component---src-pages-factsheets-index-tsx","assets":[{"name":"framework-cdc12ae707ed0f1084a8.js","size":130668},{"name":"styles.191266c70ed3461c11b7.css","size":168809},{"name":"a9a7754c-e01654b7e0389317be23.js","size":4849},{"name":"commons-8817f1dc13b8b3f15631.js","size":95151},{"name":"d9d9aac2f06cd78624aede3022e388915c13e40b-ec74eb48eac289eceb98.js","size":51358},{"name":"component---src-pages-factsheets-index-tsx-5cbb1c0331530263600b.js","size":8379}],"filteredAssets":0,"assetsSize":459214,"filteredAuxiliaryAssets":5,"auxiliaryAssetsSize":1466029},"component---src-pages-index-tsx":{"name":"component---src-pages-index-tsx","assets":[{"name":"framework-cdc12ae707ed0f1084a8.js","size":130668},{"name":"styles.191266c70ed3461c11b7.css","size":168809},{"name":"a9a7754c-e01654b7e0389317be23.js","size":4849},{"name":"cb1608f2-e6adf9bb6fd20bfed239.js","size":7589},{"name":"commons-8817f1dc13b8b3f15631.js","size":95151},{"name":"d9d9aac2f06cd78624aede3022e388915c13e40b-ec74eb48eac289eceb98.js","size":51358},{"name":"component---src-pages-index-tsx-40179d1ff62764b70cba.js","size":5043}],"filteredAssets":0,"assetsSize":463467,"filteredAuxiliaryAssets":6,"auxiliaryAssetsSize":2176005},"component---src-pages-networkinghub-tsx":{"name":"component---src-pages-networkinghub-tsx","assets":[{"name":"framework-cdc12ae707ed0f1084a8.js","size":130668},{"name":"styles.191266c70ed3461c11b7.css","size":168809},{"name":"a9a7754c-e01654b7e0389317be23.js","size":4849},{"name":"commons-8817f1dc13b8b3f15631.js","size":95151},{"name":"d9d9aac2f06cd78624aede3022e388915c13e40b-ec74eb48eac289eceb98.js","size":51358},{"name":"component---src-pages-networkinghub-tsx-0e7b71f9b6d158c8afe7.js","size":7938}],"filteredAssets":0,"assetsSize":458773,"filteredAuxiliaryAssets":5,"auxiliaryAssetsSize":1463368},"component---src-pages-news-index-tsx":{"name":"component---src-pages-news-index-tsx","assets":[{"name":"framework-cdc12ae707ed0f1084a8.js","size":130668},{"name":"styles.191266c70ed3461c11b7.css","size":168809},{"name":"a9a7754c-e01654b7e0389317be23.js","size":4849},{"name":"cb1608f2-e6adf9bb6fd20bfed239.js","size":7589},{"name":"commons-8817f1dc13b8b3f15631.js","size":95151},{"name":"d9d9aac2f06cd78624aede3022e388915c13e40b-ec74eb48eac289eceb98.js","size":51358},{"name":"1193784d5dfdff9e9c7cfab8ecb9952eee95cd8f-b7e15af1e577c9b1487e.js","size":8854},{"name":"component---src-pages-news-index-tsx-56a7313b84189234cfa2.js","size":2925}],"filteredAssets":0,"assetsSize":470203,"filteredAuxiliaryAssets":7,"auxiliaryAssetsSize":2319322},"component---src-pages-performances-index-tsx":{"name":"component---src-pages-performances-index-tsx","assets":[{"name":"framework-cdc12ae707ed0f1084a8.js","size":130668},{"name":"styles.191266c70ed3461c11b7.css","size":168809},{"name":"a9a7754c-e01654b7e0389317be23.js","size":4849},{"name":"commons-8817f1dc13b8b3f15631.js","size":95151},{"name":"d9d9aac2f06cd78624aede3022e388915c13e40b-ec74eb48eac289eceb98.js","size":51358},{"name":"component---src-pages-performances-index-tsx-30f6da72a2326062ec4c.js","size":2580}],"filteredAssets":0,"assetsSize":453415,"filteredAuxiliaryAssets":5,"auxiliaryAssetsSize":1444909},"component---src-pages-performances-perf-1-index-tsx":{"name":"component---src-pages-performances-perf-1-index-tsx","assets":[{"name":"framework-cdc12ae707ed0f1084a8.js","size":130668},{"name":"styles.191266c70ed3461c11b7.css","size":168809},{"name":"a9a7754c-e01654b7e0389317be23.js","size":4849},{"name":"commons-8817f1dc13b8b3f15631.js","size":95151},{"name":"d9d9aac2f06cd78624aede3022e388915c13e40b-ec74eb48eac289eceb98.js","size":51358},{"name":"component---src-pages-performances-perf-1-index-tsx-a02139119e104f73cdd9.js","size":1181}],"filteredAssets":0,"assetsSize":452016,"filteredAuxiliaryAssets":5,"auxiliaryAssetsSize":1441697},"component---src-pages-performances-perf-2-index-tsx":{"name":"component---src-pages-performances-perf-2-index-tsx","assets":[{"name":"framework-cdc12ae707ed0f1084a8.js","size":130668},{"name":"styles.191266c70ed3461c11b7.css","size":168809},{"name":"a9a7754c-e01654b7e0389317be23.js","size":4849},{"name":"commons-8817f1dc13b8b3f15631.js","size":95151},{"name":"d9d9aac2f06cd78624aede3022e388915c13e40b-ec74eb48eac289eceb98.js","size":51358},{"name":"component---src-pages-performances-perf-2-index-tsx-fa6c790ea0be8984da7d.js","size":1180}],"filteredAssets":0,"assetsSize":452015,"filteredAuxiliaryAssets":5,"auxiliaryAssetsSize":1441697},"component---src-pages-podcasts-index-tsx":{"name":"component---src-pages-podcasts-index-tsx","assets":[{"name":"framework-cdc12ae707ed0f1084a8.js","size":130668},{"name":"styles.191266c70ed3461c11b7.css","size":168809},{"name":"a9a7754c-e01654b7e0389317be23.js","size":4849},{"name":"commons-8817f1dc13b8b3f15631.js","size":95151},{"name":"d9d9aac2f06cd78624aede3022e388915c13e40b-ec74eb48eac289eceb98.js","size":51358},{"name":"component---src-pages-podcasts-index-tsx-b42acc904a0e9230cc09.js","size":10297}],"filteredAssets":0,"assetsSize":461132,"filteredAuxiliaryAssets":5,"auxiliaryAssetsSize":1470622},"component---src-pages-resources-tsx":{"name":"component---src-pages-resources-tsx","assets":[{"name":"framework-cdc12ae707ed0f1084a8.js","size":130668},{"name":"styles.191266c70ed3461c11b7.css","size":168809},{"name":"a9a7754c-e01654b7e0389317be23.js","size":4849},{"name":"commons-8817f1dc13b8b3f15631.js","size":95151},{"name":"d9d9aac2f06cd78624aede3022e388915c13e40b-ec74eb48eac289eceb98.js","size":51358},{"name":"component---src-pages-resources-tsx-3ddecc70eac9102b4921.js","size":8719}],"filteredAssets":0,"assetsSize":459554,"filteredAuxiliaryAssets":5,"auxiliaryAssetsSize":1464483},"component---src-pages-search-tsx":{"name":"component---src-pages-search-tsx","assets":[{"name":"framework-cdc12ae707ed0f1084a8.js","size":130668},{"name":"styles.191266c70ed3461c11b7.css","size":168809},{"name":"a9a7754c-e01654b7e0389317be23.js","size":4849},{"name":"commons-8817f1dc13b8b3f15631.js","size":95151},{"name":"d9d9aac2f06cd78624aede3022e388915c13e40b-ec74eb48eac289eceb98.js","size":51358},{"name":"component---src-pages-search-tsx-3c3fe199f68896fe92cd.js","size":26634}],"filteredAssets":0,"assetsSize":477469,"filteredAuxiliaryAssets":5,"auxiliaryAssetsSize":1532439},"component---src-pages-tools-apps-tsx":{"name":"component---src-pages-tools-apps-tsx","assets":[{"name":"framework-cdc12ae707ed0f1084a8.js","size":130668},{"name":"styles.191266c70ed3461c11b7.css","size":168809},{"name":"a9a7754c-e01654b7e0389317be23.js","size":4849},{"name":"cb1608f2-e6adf9bb6fd20bfed239.js","size":7589},{"name":"commons-8817f1dc13b8b3f15631.js","size":95151},{"name":"d9d9aac2f06cd78624aede3022e388915c13e40b-ec74eb48eac289eceb98.js","size":51358},{"name":"19cf059346695348b71b701879ad247a7424ad83-9101f486d176e4f17994.js","size":14559},{"name":"1193784d5dfdff9e9c7cfab8ecb9952eee95cd8f-b7e15af1e577c9b1487e.js","size":8854},{"name":"component---src-pages-tools-apps-tsx-64ab9b74f1096a79359f.js","size":3149}],"filteredAssets":0,"assetsSize":484986,"filteredAuxiliaryAssets":8,"auxiliaryAssetsSize":2371445},"component---src-pages-tools-components-tsx":{"name":"component---src-pages-tools-components-tsx","assets":[{"name":"framework-cdc12ae707ed0f1084a8.js","size":130668},{"name":"styles.191266c70ed3461c11b7.css","size":168809},{"name":"a9a7754c-e01654b7e0389317be23.js","size":4849},{"name":"cb1608f2-e6adf9bb6fd20bfed239.js","size":7589},{"name":"commons-8817f1dc13b8b3f15631.js","size":95151},{"name":"d9d9aac2f06cd78624aede3022e388915c13e40b-ec74eb48eac289eceb98.js","size":51358},{"name":"19cf059346695348b71b701879ad247a7424ad83-9101f486d176e4f17994.js","size":14559},{"name":"1193784d5dfdff9e9c7cfab8ecb9952eee95cd8f-b7e15af1e577c9b1487e.js","size":8854},{"name":"component---src-pages-tools-components-tsx-3fc723bce30d1172eed3.js","size":3392}],"filteredAssets":0,"assetsSize":485229,"filteredAuxiliaryAssets":8,"auxiliaryAssetsSize":2373757},"component---src-pages-visitorhub-tsx":{"name":"component---src-pages-visitorhub-tsx","assets":[{"name":"framework-cdc12ae707ed0f1084a8.js","size":130668},{"name":"styles.191266c70ed3461c11b7.css","size":168809},{"name":"a9a7754c-e01654b7e0389317be23.js","size":4849},{"name":"commons-8817f1dc13b8b3f15631.js","size":95151},{"name":"d9d9aac2f06cd78624aede3022e388915c13e40b-ec74eb48eac289eceb98.js","size":51358},{"name":"component---src-pages-visitorhub-tsx-43d37587681c12138371.js","size":8355}],"filteredAssets":0,"assetsSize":459190,"filteredAuxiliaryAssets":5,"auxiliaryAssetsSize":1463916},"component---src-pages-webinars-index-tsx":{"name":"component---src-pages-webinars-index-tsx","assets":[{"name":"framework-cdc12ae707ed0f1084a8.js","size":130668},{"name":"styles.191266c70ed3461c11b7.css","size":168809},{"name":"a9a7754c-e01654b7e0389317be23.js","size":4849},{"name":"commons-8817f1dc13b8b3f15631.js","size":95151},{"name":"d9d9aac2f06cd78624aede3022e388915c13e40b-ec74eb48eac289eceb98.js","size":51358},{"name":"component---src-pages-webinars-index-tsx-51889c31b68094af3270.js","size":10153}],"filteredAssets":0,"assetsSize":460988,"filteredAuxiliaryAssets":5,"auxiliaryAssetsSize":1470616},"component---src-templates-eshop-js":{"name":"component---src-templates-eshop-js","assets":[{"name":"framework-cdc12ae707ed0f1084a8.js","size":130668},{"name":"styles.191266c70ed3461c11b7.css","size":168809},{"name":"a9a7754c-e01654b7e0389317be23.js","size":4849},{"name":"commons-8817f1dc13b8b3f15631.js","size":95151},{"name":"d9d9aac2f06cd78624aede3022e388915c13e40b-ec74eb48eac289eceb98.js","size":51358},{"name":"component---src-templates-eshop-js-1c616cd19f308fb1e8b2.js","size":12224}],"filteredAssets":0,"assetsSize":463059,"filteredAuxiliaryAssets":5,"auxiliaryAssetsSize":1485683},"component---src-templates-exhibition-object-js":{"name":"component---src-templates-exhibition-object-js","assets":[{"name":"framework-cdc12ae707ed0f1084a8.js","size":130668},{"name":"styles.191266c70ed3461c11b7.css","size":168809},{"name":"a9a7754c-e01654b7e0389317be23.js","size":4849},{"name":"commons-8817f1dc13b8b3f15631.js","size":95151},{"name":"d9d9aac2f06cd78624aede3022e388915c13e40b-ec74eb48eac289eceb98.js","size":51358},{"name":"component---src-templates-exhibition-object-js-636cf1f52383c9305558.js","size":3066}],"filteredAssets":0,"assetsSize":453901,"filteredAuxiliaryAssets":5,"auxiliaryAssetsSize":1446428},"component---src-templates-faq-howto-js":{"name":"component---src-templates-faq-howto-js","assets":[{"name":"framework-cdc12ae707ed0f1084a8.js","size":130668},{"name":"styles.191266c70ed3461c11b7.css","size":168809},{"name":"a9a7754c-e01654b7e0389317be23.js","size":4849},{"name":"commons-8817f1dc13b8b3f15631.js","size":95151},{"name":"d9d9aac2f06cd78624aede3022e388915c13e40b-ec74eb48eac289eceb98.js","size":51358},{"name":"component---src-templates-faq-howto-js-35be4e2fd0eca17c002c.js","size":2941}],"filteredAssets":0,"assetsSize":453776,"filteredAuxiliaryAssets":5,"auxiliaryAssetsSize":1446546},"component---src-templates-toolkit-js":{"name":"component---src-templates-toolkit-js","assets":[{"name":"framework-cdc12ae707ed0f1084a8.js","size":130668},{"name":"styles.191266c70ed3461c11b7.css","size":168809},{"name":"a9a7754c-e01654b7e0389317be23.js","size":4849},{"name":"cb1608f2-e6adf9bb6fd20bfed239.js","size":7589},{"name":"commons-8817f1dc13b8b3f15631.js","size":95151},{"name":"d9d9aac2f06cd78624aede3022e388915c13e40b-ec74eb48eac289eceb98.js","size":51358},{"name":"component---src-templates-toolkit-js-9fa5dd62ee352f4901a3.js","size":122020}],"filteredAssets":0,"assetsSize":580444,"filteredAuxiliaryAssets":6,"auxiliaryAssetsSize":2782486},"component---src-templates-webinar-js":{"name":"component---src-templates-webinar-js","assets":[{"name":"framework-cdc12ae707ed0f1084a8.js","size":130668},{"name":"styles.191266c70ed3461c11b7.css","size":168809},{"name":"a9a7754c-e01654b7e0389317be23.js","size":4849},{"name":"commons-8817f1dc13b8b3f15631.js","size":95151},{"name":"d9d9aac2f06cd78624aede3022e388915c13e40b-ec74eb48eac289eceb98.js","size":51358},{"name":"component---src-templates-webinar-js-7701cb9faa1fd1a603eb.js","size":4120}],"filteredAssets":0,"assetsSize":454955,"filteredAuxiliaryAssets":5,"auxiliaryAssetsSize":1449839}},"assetsByChunkName":{"polyfill":["webpack-runtime-fc24e9dc83e30f5f4af5.js","polyfill-ff4e3d2c3de56734b40c.js"],"app":["webpack-runtime-fc24e9dc83e30f5f4af5.js","framework-cdc12ae707ed0f1084a8.js","app-5c34450b26552dd01bca.js"],"component---src-pages-404-tsx":["framework-cdc12ae707ed0f1084a8.js","styles.191266c70ed3461c11b7.css","a9a7754c-e01654b7e0389317be23.js","cb1608f2-e6adf9bb6fd20bfed239.js","commons-8817f1dc13b8b3f15631.js","d9d9aac2f06cd78624aede3022e388915c13e40b-ec74eb48eac289eceb98.js","component---src-pages-404-tsx-1c40a00572d6d52a2abf.js"],"component---src-pages-about-dataprot-tsx":["framework-cdc12ae707ed0f1084a8.js","styles.191266c70ed3461c11b7.css","a9a7754c-e01654b7e0389317be23.js","commons-8817f1dc13b8b3f15631.js","d9d9aac2f06cd78624aede3022e388915c13e40b-ec74eb48eac289eceb98.js","component---src-pages-about-dataprot-tsx-972697101debce014674.js"],"component---src-pages-about-imprint-tsx":["framework-cdc12ae707ed0f1084a8.js","styles.191266c70ed3461c11b7.css","a9a7754c-e01654b7e0389317be23.js","commons-8817f1dc13b8b3f15631.js","d9d9aac2f06cd78624aede3022e388915c13e40b-ec74eb48eac289eceb98.js","component---src-pages-about-imprint-tsx-7e69737dab1ce7a1123e.js"],"component---src-pages-about-index-tsx":["framework-cdc12ae707ed0f1084a8.js","styles.191266c70ed3461c11b7.css","a9a7754c-e01654b7e0389317be23.js","commons-8817f1dc13b8b3f15631.js","d9d9aac2f06cd78624aede3022e388915c13e40b-ec74eb48eac289eceb98.js","component---src-pages-about-index-tsx-df2bae44c065a443a78e.js"],"component---src-pages-about-team-tsx":["framework-cdc12ae707ed0f1084a8.js","styles.191266c70ed3461c11b7.css","a9a7754c-e01654b7e0389317be23.js","commons-8817f1dc13b8b3f15631.js","d9d9aac2f06cd78624aede3022e388915c13e40b-ec74eb48eac289eceb98.js","component---src-pages-about-team-tsx-d283fe40da3f04233a3c.js"],"component---src-pages-cms-index-tsx":["framework-cdc12ae707ed0f1084a8.js","styles.191266c70ed3461c11b7.css","a9a7754c-e01654b7e0389317be23.js","commons-8817f1dc13b8b3f15631.js","d9d9aac2f06cd78624aede3022e388915c13e40b-ec74eb48eac289eceb98.js","component---src-pages-cms-index-tsx-eed145157b0403b82486.js"],"component---src-pages-collection-tsx":["framework-cdc12ae707ed0f1084a8.js","styles.191266c70ed3461c11b7.css","a9a7754c-e01654b7e0389317be23.js","cb1608f2-e6adf9bb6fd20bfed239.js","commons-8817f1dc13b8b3f15631.js","d9d9aac2f06cd78624aede3022e388915c13e40b-ec74eb48eac289eceb98.js","component---src-pages-collection-tsx-129f2bb0cf3de2bcf453.js"],"component---src-pages-demo-tsx":["framework-cdc12ae707ed0f1084a8.js","styles.191266c70ed3461c11b7.css","a9a7754c-e01654b7e0389317be23.js","commons-8817f1dc13b8b3f15631.js","d9d9aac2f06cd78624aede3022e388915c13e40b-ec74eb48eac289eceb98.js","component---src-pages-demo-tsx-e16ebc523747eeca418d.js"],"component---src-pages-doc-authorization-tsx":["framework-cdc12ae707ed0f1084a8.js","styles.191266c70ed3461c11b7.css","a9a7754c-e01654b7e0389317be23.js","commons-8817f1dc13b8b3f15631.js","d9d9aac2f06cd78624aede3022e388915c13e40b-ec74eb48eac289eceb98.js","701dc261555fcc3a9aac6dcd63ecb7e55ca62dbb-c11d7d1f21ef991cac01.js","component---src-pages-doc-authorization-tsx-f27885b1532db5bbc9f9.js"],"component---src-pages-doc-datamodel-tsx":["framework-cdc12ae707ed0f1084a8.js","styles.191266c70ed3461c11b7.css","a9a7754c-e01654b7e0389317be23.js","commons-8817f1dc13b8b3f15631.js","d9d9aac2f06cd78624aede3022e388915c13e40b-ec74eb48eac289eceb98.js","component---src-pages-doc-datamodel-tsx-50ed787cd8bb51c2f033.js"],"component---src-pages-doc-faq-tsx":["framework-cdc12ae707ed0f1084a8.js","styles.191266c70ed3461c11b7.css","a9a7754c-e01654b7e0389317be23.js","commons-8817f1dc13b8b3f15631.js","d9d9aac2f06cd78624aede3022e388915c13e40b-ec74eb48eac289eceb98.js","701dc261555fcc3a9aac6dcd63ecb7e55ca62dbb-c11d7d1f21ef991cac01.js","component---src-pages-doc-faq-tsx-a5257416cb25f374a339.js"],"component---src-pages-doc-howto-tsx":["framework-cdc12ae707ed0f1084a8.js","styles.191266c70ed3461c11b7.css","a9a7754c-e01654b7e0389317be23.js","commons-8817f1dc13b8b3f15631.js","d9d9aac2f06cd78624aede3022e388915c13e40b-ec74eb48eac289eceb98.js","701dc261555fcc3a9aac6dcd63ecb7e55ca62dbb-c11d7d1f21ef991cac01.js","component---src-pages-doc-howto-tsx-d7743cea65f64cc16e5b.js"],"component---src-pages-doc-index-tsx":["framework-cdc12ae707ed0f1084a8.js","styles.191266c70ed3461c11b7.css","a9a7754c-e01654b7e0389317be23.js","commons-8817f1dc13b8b3f15631.js","d9d9aac2f06cd78624aede3022e388915c13e40b-ec74eb48eac289eceb98.js","component---src-pages-doc-index-tsx-0fdaa484a15b2e77ab52.js"],"component---src-pages-eshop-index-tsx":["framework-cdc12ae707ed0f1084a8.js","styles.191266c70ed3461c11b7.css","a9a7754c-e01654b7e0389317be23.js","commons-8817f1dc13b8b3f15631.js","d9d9aac2f06cd78624aede3022e388915c13e40b-ec74eb48eac289eceb98.js","19cf059346695348b71b701879ad247a7424ad83-9101f486d176e4f17994.js","component---src-pages-eshop-index-tsx-086e9ecaffc69f738a69.js"],"component---src-pages-events-index-tsx":["framework-cdc12ae707ed0f1084a8.js","styles.191266c70ed3461c11b7.css","a9a7754c-e01654b7e0389317be23.js","commons-8817f1dc13b8b3f15631.js","d9d9aac2f06cd78624aede3022e388915c13e40b-ec74eb48eac289eceb98.js","component---src-pages-events-index-tsx-9d236a385a63020aa71e.js"],"component---src-pages-exhibitions-identities-final-page-index-tsx":["framework-cdc12ae707ed0f1084a8.js","styles.191266c70ed3461c11b7.css","commons-8817f1dc13b8b3f15631.js","fa7506b98c3597319d30ed7c7d3a27e4fe8c02d7-572af4f1cd9f19672a94.js","19cf059346695348b71b701879ad247a7424ad83-9101f486d176e4f17994.js","component---src-pages-exhibitions-identities-final-page-index-tsx-cf180af46ae31d4a218b.js"],"component---src-pages-exhibitions-identities-intro-index-tsx":["framework-cdc12ae707ed0f1084a8.js","styles.191266c70ed3461c11b7.css","commons-8817f1dc13b8b3f15631.js","fa7506b98c3597319d30ed7c7d3a27e4fe8c02d7-572af4f1cd9f19672a94.js","component---src-pages-exhibitions-identities-intro-index-tsx-a7c9a494c5e360bc2168.js"],"component---src-pages-exhibitions-identities-obj-one-index-tsx":["framework-cdc12ae707ed0f1084a8.js","styles.191266c70ed3461c11b7.css","commons-8817f1dc13b8b3f15631.js","fa7506b98c3597319d30ed7c7d3a27e4fe8c02d7-572af4f1cd9f19672a94.js","component---src-pages-exhibitions-identities-obj-one-index-tsx-173c04837a6c78c71803.js"],"component---src-pages-exhibitions-identities-question-four-index-tsx":["framework-cdc12ae707ed0f1084a8.js","styles.191266c70ed3461c11b7.css","commons-8817f1dc13b8b3f15631.js","fa7506b98c3597319d30ed7c7d3a27e4fe8c02d7-572af4f1cd9f19672a94.js","19cf059346695348b71b701879ad247a7424ad83-9101f486d176e4f17994.js","component---src-pages-exhibitions-identities-question-four-index-tsx-a9a8176fbf0fde3e2bf3.js"],"component---src-pages-exhibitions-identities-question-one-index-tsx":["framework-cdc12ae707ed0f1084a8.js","styles.191266c70ed3461c11b7.css","commons-8817f1dc13b8b3f15631.js","fa7506b98c3597319d30ed7c7d3a27e4fe8c02d7-572af4f1cd9f19672a94.js","component---src-pages-exhibitions-identities-question-one-index-tsx-134cc1b84c1cf222c533.js"],"component---src-pages-exhibitions-index-tsx":["framework-cdc12ae707ed0f1084a8.js","styles.191266c70ed3461c11b7.css","commons-8817f1dc13b8b3f15631.js","fa7506b98c3597319d30ed7c7d3a27e4fe8c02d7-572af4f1cd9f19672a94.js","component---src-pages-exhibitions-index-tsx-9f41d7998cd3de55d0d1.js"],"component---src-pages-factsheets-index-tsx":["framework-cdc12ae707ed0f1084a8.js","styles.191266c70ed3461c11b7.css","a9a7754c-e01654b7e0389317be23.js","commons-8817f1dc13b8b3f15631.js","d9d9aac2f06cd78624aede3022e388915c13e40b-ec74eb48eac289eceb98.js","component---src-pages-factsheets-index-tsx-5cbb1c0331530263600b.js"],"component---src-pages-index-tsx":["framework-cdc12ae707ed0f1084a8.js","styles.191266c70ed3461c11b7.css","a9a7754c-e01654b7e0389317be23.js","cb1608f2-e6adf9bb6fd20bfed239.js","commons-8817f1dc13b8b3f15631.js","d9d9aac2f06cd78624aede3022e388915c13e40b-ec74eb48eac289eceb98.js","component---src-pages-index-tsx-40179d1ff62764b70cba.js"],"component---src-pages-networkinghub-tsx":["framework-cdc12ae707ed0f1084a8.js","styles.191266c70ed3461c11b7.css","a9a7754c-e01654b7e0389317be23.js","commons-8817f1dc13b8b3f15631.js","d9d9aac2f06cd78624aede3022e388915c13e40b-ec74eb48eac289eceb98.js","component---src-pages-networkinghub-tsx-0e7b71f9b6d158c8afe7.js"],"component---src-pages-news-index-tsx":["framework-cdc12ae707ed0f1084a8.js","styles.191266c70ed3461c11b7.css","a9a7754c-e01654b7e0389317be23.js","cb1608f2-e6adf9bb6fd20bfed239.js","commons-8817f1dc13b8b3f15631.js","d9d9aac2f06cd78624aede3022e388915c13e40b-ec74eb48eac289eceb98.js","1193784d5dfdff9e9c7cfab8ecb9952eee95cd8f-b7e15af1e577c9b1487e.js","component---src-pages-news-index-tsx-56a7313b84189234cfa2.js"],"component---src-pages-performances-index-tsx":["framework-cdc12ae707ed0f1084a8.js","styles.191266c70ed3461c11b7.css","a9a7754c-e01654b7e0389317be23.js","commons-8817f1dc13b8b3f15631.js","d9d9aac2f06cd78624aede3022e388915c13e40b-ec74eb48eac289eceb98.js","component---src-pages-performances-index-tsx-30f6da72a2326062ec4c.js"],"component---src-pages-performances-perf-1-index-tsx":["framework-cdc12ae707ed0f1084a8.js","styles.191266c70ed3461c11b7.css","a9a7754c-e01654b7e0389317be23.js","commons-8817f1dc13b8b3f15631.js","d9d9aac2f06cd78624aede3022e388915c13e40b-ec74eb48eac289eceb98.js","component---src-pages-performances-perf-1-index-tsx-a02139119e104f73cdd9.js"],"component---src-pages-performances-perf-2-index-tsx":["framework-cdc12ae707ed0f1084a8.js","styles.191266c70ed3461c11b7.css","a9a7754c-e01654b7e0389317be23.js","commons-8817f1dc13b8b3f15631.js","d9d9aac2f06cd78624aede3022e388915c13e40b-ec74eb48eac289eceb98.js","component---src-pages-performances-perf-2-index-tsx-fa6c790ea0be8984da7d.js"],"component---src-pages-podcasts-index-tsx":["framework-cdc12ae707ed0f1084a8.js","styles.191266c70ed3461c11b7.css","a9a7754c-e01654b7e0389317be23.js","commons-8817f1dc13b8b3f15631.js","d9d9aac2f06cd78624aede3022e388915c13e40b-ec74eb48eac289eceb98.js","component---src-pages-podcasts-index-tsx-b42acc904a0e9230cc09.js"],"component---src-pages-resources-tsx":["framework-cdc12ae707ed0f1084a8.js","styles.191266c70ed3461c11b7.css","a9a7754c-e01654b7e0389317be23.js","commons-8817f1dc13b8b3f15631.js","d9d9aac2f06cd78624aede3022e388915c13e40b-ec74eb48eac289eceb98.js","component---src-pages-resources-tsx-3ddecc70eac9102b4921.js"],"component---src-pages-search-tsx":["framework-cdc12ae707ed0f1084a8.js","styles.191266c70ed3461c11b7.css","a9a7754c-e01654b7e0389317be23.js","commons-8817f1dc13b8b3f15631.js","d9d9aac2f06cd78624aede3022e388915c13e40b-ec74eb48eac289eceb98.js","component---src-pages-search-tsx-3c3fe199f68896fe92cd.js"],"component---src-pages-tools-apps-tsx":["framework-cdc12ae707ed0f1084a8.js","styles.191266c70ed3461c11b7.css","a9a7754c-e01654b7e0389317be23.js","cb1608f2-e6adf9bb6fd20bfed239.js","commons-8817f1dc13b8b3f15631.js","d9d9aac2f06cd78624aede3022e388915c13e40b-ec74eb48eac289eceb98.js","19cf059346695348b71b701879ad247a7424ad83-9101f486d176e4f17994.js","1193784d5dfdff9e9c7cfab8ecb9952eee95cd8f-b7e15af1e577c9b1487e.js","component---src-pages-tools-apps-tsx-64ab9b74f1096a79359f.js"],"component---src-pages-tools-components-tsx":["framework-cdc12ae707ed0f1084a8.js","styles.191266c70ed3461c11b7.css","a9a7754c-e01654b7e0389317be23.js","cb1608f2-e6adf9bb6fd20bfed239.js","commons-8817f1dc13b8b3f15631.js","d9d9aac2f06cd78624aede3022e388915c13e40b-ec74eb48eac289eceb98.js","19cf059346695348b71b701879ad247a7424ad83-9101f486d176e4f17994.js","1193784d5dfdff9e9c7cfab8ecb9952eee95cd8f-b7e15af1e577c9b1487e.js","component---src-pages-tools-components-tsx-3fc723bce30d1172eed3.js"],"component---src-pages-visitorhub-tsx":["framework-cdc12ae707ed0f1084a8.js","styles.191266c70ed3461c11b7.css","a9a7754c-e01654b7e0389317be23.js","commons-8817f1dc13b8b3f15631.js","d9d9aac2f06cd78624aede3022e388915c13e40b-ec74eb48eac289eceb98.js","component---src-pages-visitorhub-tsx-43d37587681c12138371.js"],"component---src-pages-webinars-index-tsx":["framework-cdc12ae707ed0f1084a8.js","styles.191266c70ed3461c11b7.css","a9a7754c-e01654b7e0389317be23.js","commons-8817f1dc13b8b3f15631.js","d9d9aac2f06cd78624aede3022e388915c13e40b-ec74eb48eac289eceb98.js","component---src-pages-webinars-index-tsx-51889c31b68094af3270.js"],"component---src-templates-eshop-js":["framework-cdc12ae707ed0f1084a8.js","styles.191266c70ed3461c11b7.css","a9a7754c-e01654b7e0389317be23.js","commons-8817f1dc13b8b3f15631.js","d9d9aac2f06cd78624aede3022e388915c13e40b-ec74eb48eac289eceb98.js","component---src-templates-eshop-js-1c616cd19f308fb1e8b2.js"],"component---src-templates-exhibition-object-js":["framework-cdc12ae707ed0f1084a8.js","styles.191266c70ed3461c11b7.css","a9a7754c-e01654b7e0389317be23.js","commons-8817f1dc13b8b3f15631.js","d9d9aac2f06cd78624aede3022e388915c13e40b-ec74eb48eac289eceb98.js","component---src-templates-exhibition-object-js-636cf1f52383c9305558.js"],"component---src-templates-faq-howto-js":["framework-cdc12ae707ed0f1084a8.js","styles.191266c70ed3461c11b7.css","a9a7754c-e01654b7e0389317be23.js","commons-8817f1dc13b8b3f15631.js","d9d9aac2f06cd78624aede3022e388915c13e40b-ec74eb48eac289eceb98.js","component---src-templates-faq-howto-js-35be4e2fd0eca17c002c.js"],"component---src-templates-toolkit-js":["framework-cdc12ae707ed0f1084a8.js","styles.191266c70ed3461c11b7.css","a9a7754c-e01654b7e0389317be23.js","cb1608f2-e6adf9bb6fd20bfed239.js","commons-8817f1dc13b8b3f15631.js","d9d9aac2f06cd78624aede3022e388915c13e40b-ec74eb48eac289eceb98.js","component---src-templates-toolkit-js-9fa5dd62ee352f4901a3.js"],"component---src-templates-webinar-js":["framework-cdc12ae707ed0f1084a8.js","styles.191266c70ed3461c11b7.css","a9a7754c-e01654b7e0389317be23.js","commons-8817f1dc13b8b3f15631.js","d9d9aac2f06cd78624aede3022e388915c13e40b-ec74eb48eac289eceb98.js","component---src-templates-webinar-js-7701cb9faa1fd1a603eb.js"]},"childAssetsByChunkName":{}}